starframe/__init__.py
starframe/starframe.py
starframe-0.0.1.dist-info/LICENSE
starframe-0.0.1.dist-info/METADATA
starframe-0.0.1.dist-info/WHEEL
starframe-0.0.1.dist-info/top_level.txt
starframe-0.0.1.dist-info/RECORD
