Metadata-Version: 2.1
Name: starframe
Version: 0.0.1
Summary: Extension of polars dataframe to stars schema
Author-email: Jacek Pliszka <jacek.pliszka@gmail.com>
License: MIT License
Project-URL: Homepage, https://github.com/JacekPliszka/starframe
Project-URL: Documentation, https://github.com/JacekPliszka/starframe
Project-URL: Repository, https://github.com/JacekPliszka/starframe
Project-URL: Changelog, https://github.com/JacekPliszka/starframe
Keywords: dataframe,polars
Classifier: Development Status :: 1 - Planning
Classifier: Environment :: Console
Classifier: Intended Audience :: Science/Research
Classifier: License :: OSI Approved :: MIT License
Classifier: Operating System :: OS Independent
Classifier: Programming Language :: Python
Classifier: Programming Language :: Python :: 3
Classifier: Programming Language :: Python :: 3 :: Only
Classifier: Programming Language :: Python :: 3.8
Classifier: Programming Language :: Python :: 3.9
Classifier: Programming Language :: Python :: 3.10
Classifier: Programming Language :: Python :: 3.11
Classifier: Topic :: Scientific/Engineering
Requires-Python: >=3.8
License-File: LICENSE
